ptbtest/callbackquerygenerator.py
ptbtest/chatgenerator.py
ptbtest/entityparser.py
ptbtest/errors.py
ptbtest/inlinequerygenerator.py
ptbtest/messagegenerator.py
ptbtest/mockbot.py
ptbtest/ptbgenerator.py
ptbtest/updategenerator.py
ptbtest/usergenerator.py
ptbtest/__init__.py
ptbtest-1.3.dist-info/DESCRIPTION.rst
ptbtest-1.3.dist-info/METADATA
ptbtest-1.3.dist-info/metadata.json
ptbtest-1.3.dist-info/RECORD
ptbtest-1.3.dist-info/top_level.txt
ptbtest-1.3.dist-info/WHEEL
